Metadata-Version: 2.1
Name: cincan-registry
Version: 0.3.0
Summary: CinCan Registry: a tool for listing available CinCan tools, their versions and possible updates.
Home-page: https://gitlab.com/cincan/cincan-registry
Author: Niklas Saari
Author-email: niklas.saari@tutanota.com
License: UNKNOWN
Platform: UNKNOWN
Classifier: Programming Language :: Python :: 3
Classifier: License :: OSI Approved :: MIT License
Classifier: Operating System :: Unix
Requires-Python: >=3.6
Requires-Dist: docker (>=4.4.1)
Requires-Dist: python-gitlab (>=2.7.1)
Requires-Dist: pyyaml
Requires-Dist: requests
